testgen/__init__.py
testgen/analyzer/__init__.py
testgen/analyzer/ast_analyzer.py
testgen/analyzer/contracts/__init__.py
testgen/analyzer/contracts/contract.py
testgen/analyzer/contracts/no_exception_contract.py
testgen/analyzer/contracts/nonnull_contract.py
testgen/analyzer/fuzz_analyzer.py
testgen/analyzer/random_feedback_analyzer.py
testgen/analyzer/reinforcement_analyzer.py
testgen/analyzer/test_case_analyzer.py
testgen/analyzer/test_case_analyzer_context.py
testgen/controller/__init__.py
testgen/controller/cli_controller.py
testgen/controller/docker_controller.py
testgen/db/__init__.py
testgen/db/dao.py
testgen/db/dao_impl.py
testgen/db/db.py
testgen/docker/Dockerfile
testgen/generator/__init__.py
testgen/generator/code_generator.py
testgen/generator/doctest_generator.py
testgen/generator/generator.py
testgen/generator/pytest_generator.py
testgen/generator/test_generator.py
testgen/generator/unit_test_generator.py
testgen/main.py
testgen/models/__init__.py
testgen/models/analysis_context.py
testgen/models/coverage_data.py
testgen/models/db_test_case.py
testgen/models/function.py
testgen/models/function_metadata.py
testgen/models/generator_context.py
testgen/models/source_file.py
testgen/models/test_case.py
testgen/models/test_result.py
testgen/models/test_suite.py
testgen/reinforcement/__init__.py
testgen/reinforcement/abstract_state.py
testgen/reinforcement/agent.py
testgen/reinforcement/environment.py
testgen/reinforcement/statement_coverage_state.py
testgen/service/__init__.py
testgen/service/analysis_service.py
testgen/service/cfg_service.py
testgen/service/coverage_service.py
testgen/service/db_service.py
testgen/service/generator_service.py
testgen/service/logging_service.py
testgen/service/service.py
testgen/service/test_executor_service.py
testgen/tree/__init__.py
testgen/tree/node.py
testgen/tree/tree_utils.py
testgen/util/__init__.py
testgen/util/coverage_utils.py
testgen/util/coverage_visualizer.py
testgen/util/file_utils.py
testgenie_py-0.3.9.dist-info/METADATA
testgenie_py-0.3.9.dist-info/WHEEL
testgenie_py-0.3.9.dist-info/entry_points.txt
testgenie_py-0.3.9.dist-info/RECORD
